my_first_package/__init__.py
my_first_package/module.py
FIRST_package_ozdi-0.0.1.dist-info/LICENCE
FIRST_package_ozdi-0.0.1.dist-info/METADATA
FIRST_package_ozdi-0.0.1.dist-info/WHEEL
FIRST_package_ozdi-0.0.1.dist-info/top_level.txt
FIRST_package_ozdi-0.0.1.dist-info/RECORD
